<?xml version="1.0"?>
<Document style="helpdocument">
	<p style="htitle">Sentieri</p>
	<p style="hp">I sentieri sono la piu` semplice e la piu`
	  economica delle possibilita` di trasporto. Hanno la piu`
	  bassa capacita`. I sentieri non producono inquinamento.</p>
	
	<p style="hp">Questo e` un sentiero</p>
	<img src="images/tiles/trackud.png" halign="center"/>
	<p style="hp">e questa e` la sua icona</p>
	<img src="images/gui/buttonpanel/transport/tracks.png" halign="center"/>
	
	<p style="hsubtitle">Vedi anche:</p>
	<li><a href="transport">Trasporti</a></li>
	<li><a href="commune">Commune</a></li>
</Document>
